{
  "name": "Epstein Theme",
  "description": "Epstein PNG Theme",
  "category": "Themes",
  "version": "1.0.0",
  "commit": "1ddff420718a200341f48ba50af1326e63721b2b",
  "owner": "CreeperRick",
  "repo": "BruceStore",
  "supported-screen-size": "320x170",
  "path": "/Theme_Epstein/PNG",
  "files": [
    {
      "source": "Theme_Epstein.json",
      "destination": "Epstein.json"
    },
    "BLE.png",
    "Clock.png",
    "Config.png",
    "Connect.png",
    "Ethernet.png",
    "FM.png",
    "Files.png",
    "Map.png",
    "IR.png",
    "JS.png",
    "LoRa.png",
    "NRF24.png",
    "Others.png",
    "RF.png",
    "RFID.png",
    "WiFi.png"
  ]
}
